{"About node Flags": "index.html#about-node-flags", "About Option Types": "index.html#about-option-types", "About V8 Flags": "index.html#about-v8-flags", "after()": "index.html#hooks", "afterEach()": "index.html#hooks", "Arrow Functions": "index.html#arrow-functions", "Assertions": "index.html#assertions", "Asynchronous Code": "index.html#asynchronous-code", "Asynchronous Hooks": "index.html#asynchronous-hooks", "Available Root Hooks": "index.html#available-root-hooks", "BDD": "index.html#bdd", "before()": "index.html#hooks", "beforeEach()": "index.html#hooks", "Browser Configuration": "index.html#browser-configuration", "Browser-based notifications": "index.html#browser-based-notifications", "Browser-specific Option(s)": "index.html#browser-specific-options", "Caveats About Testing in Parallel": "index.html#caveats-about-testing-in-parallel", "Command-Line Usage": "index.html#command-line-usage", "Configuration Format": "index.html#configuration-format", "Configuring Mocha (Node.js)": "index.html#configuring-mocha-nodejs", "context()": "index.html#bdd", "Current Limitations": "index.html#current-limitations", "Custom Locations": "index.html#custom-locations", "Defining a Root Hook Plugin": "index.html#defining-a-root-hook-plugin", "Delayed Root Suite": "index.html#delayed-root-suite", "describe()": "index.html#bdd", "Describing Hooks": "index.html#describing-hooks", "Desktop Notification Support": "index.html#desktop-notification-support", "Detects Multiple Calls to done()": "index.html#detects-multiple-calls-to-done", "Diffs": "index.html#diffs", "Doc": "index.html#doc", "done()": "index.html#asynchronous-code", "Dot Matrix": "index.html#dot-matrix", "Dynamically Generating Tests": "index.html#dynamically-generating-tests", "Editor Plugins": "index.html#editor-plugins", "Emacs": "index.html#emacs", "Error Codes": "index.html#error-codes", "Exclusive Tests": "index.html#exclusive-tests", "Exclusive Tests are Disallowed": "index.html#exclusive-tests-are-disallowed", "exports": "index.html#exports", "Exports": "index.html#exports", "Extending Configuration": "index.html#extending-configuration", "File Order is Non-Deterministic": "index.html#file-order-is-non-deterministic", "Global Fixtures": "index.html#global-fixtures", "Global Setup Fixtures": "index.html#global-setup-fixtures", "Global Teardown Fixtures": "index.html#global-teardown-fixtures", "Grep": "index.html#grep", "Hook-level": "index.html#hook-level", "Hooks": "index.html#hooks", "HTML Reporter": "index.html#html-reporter", "Ignoring Config Files": "index.html#ignoring-config-files", "Inclusive Tests": "index.html#inclusive-tests", "Interfaces": "index.html#interfaces", "it()": "index.html#bdd", "JetBrains": "index.html#jetbrains", "JSON": "index.html#json", "JSON Stream": "index.html#json-stream", "Landing Strip": "index.html#landing-strip", "Limited Reporter API for Third-Party Reporters": "index.html#limited-reporter-api-for-third-party-reporters", "List": "index.html#list", "Markdown": "index.html#markdown", "Merging": "index.html#merging", "Migrating a Library to use Root Hook PLugins": "index.html#migrating-a-library-to-use-root-hook-plugins", "Migrating Tests to use Root Hook Plugins": "index.html#migrating-tests-to-use-root-hook-plugins", "Min": "index.html#min", "mocha cli options": "index.html#command-line-usage", "Mocha Sidebar (VS Code)": "index.html#mocha-sidebar-vs-code", "mocha.checkLeaks()": "index.html#running-mocha-in-the-browser", "mocha.globals()": "index.html#running-mocha-in-the-browser", "mocha.run()": "index.html#running-mocha-in-the-browser", "mocha.setup()": "index.html#running-mocha-in-the-browser", "Multiple Root Hook Plugins": "index.html#multiple-root-hook-plugins", "Multiple Root Hooks in a Single Plugin": "index.html#multiple-root-hooks-in-a-single-plugin", "No Browser Support": "index.html#no-browser-support", "Node-based notifications": "index.html#node-based-notifications", "Node.JS native ESM support": "index.html#nodejs-native-esm-support", "Nyan": "index.html#nyan", "only()": "index.html#exclusive-tests", "Parallel Mode": "index.html#parallel-mode", "Parallel Tests": "index.html#parallel-tests", "Pending Tests": "index.html#pending-tests", "Priorities": "index.html#priorities", "Progress": "index.html#progress", "QUnit": "index.html#qunit", "Reporter Limitations": "index.html#reporter-limitations", "Reporters": "index.html#reporters", "Reporting": "index.html#reporting", "require": "index.html#require", "Require": "index.html#require", "Retry Tests": "index.html#retry-tests", "Root Hook Plugins": "index.html#root-hook-plugins", "Root Hook Plugins Can Export a Function": "index.html#root-hook-plugins-can-export-a-function", "Root Hooks Are Not Global": "index.html#root-hooks-are-not-global", "Root-Level Hooks": "index.html#root-level-hooks", "Run Cycle Overview": "index.html#run-cycle-overview", "run()": "index.html#delayed-root-suite", "Running Mocha in the Browser": "index.html#running-mocha-in-the-browser", "Serial Mode": "index.html#serial-mode", "setup()": "index.html#hooks", "skip()": "index.html#inclusive-tests", "Spec": "index.html#spec", "specify()": "index.html#bdd", "suite()": "index.html#tdd", "Suite-level": "index.html#suite-level", "suiteSetup()": "index.html#hooks", "suiteTeardown()": "index.html#hooks", "Synchronous Code": "index.html#synchronous-code", "TAP": "index.html#tap", "TDD": "index.html#tdd", "teardown()": "index.html#hooks", "Test duration": "index.html#test-duration", "Test Duration Variability": "index.html#test-duration-variability", "Test Fixture Decision-Tree Wizard Thing": "index.html#test-fixture-decision-tree-wizard-thing", "test()": "index.html#tdd", "Test-level": "index.html#test-level", "TextMate": "index.html#textmate", "The test/ Directory": "index.html#the-test-directory", "Third-Party Reporters": "index.html#third-party-reporters", "timeout()": "index.html#timeouts", "Timeouts": "index.html#timeouts", "Troubleshooting Parallel Mode": "index.html#troubleshooting-parallel-mode", "Using async / await": "index.html#using-async-await", "Wallaby.js": "index.html#wallabyjs", "When Not To Use Global Fixtures": "index.html#when-not-to-use-global-fixtures", "When To Use Global Fixtures": "index.html#when-to-use-global-fixtures", "Working with Promises": "index.html#working-with-promises", "XUnit": "index.html#xunit", "\u201cBail\u201d is \u201cBest Effort\u201d": "index.html#bail-is-best-effort"}