{"action": "manifest.json/action.html", "action.ColorArray": "api/action/colorarray.html", "action.disable()": "api/action/disable.html", "action.enable()": "api/action/enable.html", "action.getBadgeBackgroundColor()": "api/action/getbadgebackgroundcolor.html", "action.getBadgeText()": "api/action/getbadgetext.html", "action.getBadgeTextColor()": "api/action/getbadgetextcolor.html", "action.getPopup()": "api/action/getpopup.html", "action.getTitle()": "api/action/gettitle.html", "action.ImageDataType": "api/action/imagedatatype.html", "action.isEnabled()": "api/action/isenabled.html", "action.onClicked": "api/action/onclicked.html", "action.openPopup()": "api/action/openpopup.html", "action.setBadgeBackgroundColor()": "api/action/setbadgebackgroundcolor.html", "action.setBadgeText()": "api/action/setbadgetext.html", "action.setBadgeTextColor()": "api/action/setbadgetextcolor.html", "action.setIcon()": "api/action/seticon.html", "action.setPopup()": "api/action/setpopup.html", "action.setTitle()": "api/action/settitle.html", "Add a button to the toolbar": "add_a_button_to_the_toolbar.html", "Address bar button": "user_interface/page_actions.html", "Address bar suggestions": "user_interface/omnibox.html", "alarms": "api/alarms.html", "alarms.Alarm": "api/alarms/alarm.html", "alarms.clear()": "api/alarms/clear.html", "alarms.clearAll()": "api/alarms/clearall.html", "alarms.create()": "api/alarms/create.html", "alarms.get()": "api/alarms/get.html", "alarms.getAll()": "api/alarms/getall.html", "alarms.onAlarm": "api/alarms/onalarm.html", "Anatomy of an extension": "anatomy_of_a_webextension.html", "author": "manifest.json/author.html", "background": "manifest.json/background.html", "Background scripts": "background_scripts.html", "bookmarks": "api/bookmarks.html", "bookmarks.BookmarkTreeNode": "api/bookmarks/bookmarktreenode.html", "bookmarks.BookmarkTreeNodeType": "api/bookmarks/bookmarktreenodetype.html", "bookmarks.BookmarkTreeNodeUnmodifiable": "api/bookmarks/bookmarktreenodeunmodifiable.html", "bookmarks.create()": "api/bookmarks/create.html", "bookmarks.CreateDetails": "api/bookmarks/createdetails.html", "bookmarks.get()": "api/bookmarks/get.html", "bookmarks.getChildren()": "api/bookmarks/getchildren.html", "bookmarks.getRecent()": "api/bookmarks/getrecent.html", "bookmarks.getSubTree()": "api/bookmarks/getsubtree.html", "bookmarks.getTree()": "api/bookmarks/gettree.html", "bookmarks.move()": "api/bookmarks/move.html", "bookmarks.onChanged": "api/bookmarks/onchanged.html", "bookmarks.onChildrenReordered": "api/bookmarks/onchildrenreordered.html", "bookmarks.onCreated": "api/bookmarks/oncreated.html", "bookmarks.onImportBegan": "api/bookmarks/onimportbegan.html", "bookmarks.onImportEnded": "api/bookmarks/onimportended.html", "bookmarks.onMoved": "api/bookmarks/onmoved.html", "bookmarks.onRemoved": "api/bookmarks/onremoved.html", "bookmarks.remove()": "api/bookmarks/remove.html", "bookmarks.removeTree()": "api/bookmarks/removetree.html", "bookmarks.search()": "api/bookmarks/search.html", "bookmarks.update()": "api/bookmarks/update.html", "Browser actions": "browser_actions.html", "Browser compatibility for manifest.json": "browser_compatibility_for_manifest.json.html", "Browser styles": "user_interface/browser_styles.html", "Browser support for JavaScript APIs": "browser_support_for_javascript_apis.html", "browser_action": "manifest.json/browser_action.html", "browser_specific_settings": "manifest.json/browser_specific_settings.html", "browserAction": "api/browseraction.html", "browserAction.ColorArray": "api/browseraction/colorarray.html", "browserAction.disable()": "api/browseraction/disable.html", "browserAction.enable()": "api/browseraction/enable.html", "browserAction.getBadgeBackgroundColor()": "api/browseraction/getbadgebackgroundcolor.html", "browserAction.getBadgeText()": "api/browseraction/getbadgetext.html", "browserAction.getBadgeTextColor()": "api/browseraction/getbadgetextcolor.html", "browserAction.getPopup()": "api/browseraction/getpopup.html", "browserAction.getTitle()": "api/browseraction/gettitle.html", "browserAction.ImageDataType": "api/browseraction/imagedatatype.html", "browserAction.isEnabled()": "api/browseraction/isenabled.html", "browserAction.onClicked": "api/browseraction/onclicked.html", "browserAction.openPopup()": "api/browseraction/openpopup.html", "browserAction.setBadgeBackgroundColor()": "api/browseraction/setbadgebackgroundcolor.html", "browserAction.setBadgeText()": "api/browseraction/setbadgetext.html", "browserAction.setBadgeTextColor()": "api/browseraction/setbadgetextcolor.html", "browserAction.setIcon()": "api/browseraction/seticon.html", "browserAction.setPopup()": "api/browseraction/setpopup.html", "browserAction.setTitle()": "api/browseraction/settitle.html", "BrowserSetting": "api/types/browsersetting.html", "BrowserSetting.onChange": "api/types/browsersetting/onchange.html", "browserSettings": "api/browsersettings.html", "browserSettings.allowPopupsForUserEvents": "api/browsersettings/allowpopupsforuserevents.html", "browserSettings.cacheEnabled": "api/browsersettings/cacheenabled.html", "browserSettings.closeTabsByDoubleClick": "api/browsersettings/closetabsbydoubleclick.html", "browserSettings.colorManagement": "api/browsersettings/colormanagement.html", "browserSettings.contextMenuShowEvent": "api/browsersettings/contextmenushowevent.html", "browserSettings.ftpProtocolEnabled": "api/browsersettings/ftpprotocolenabled.html", "browserSettings.homepageOverride": "api/browsersettings/homepageoverride.html", "browserSettings.imageAnimationBehavior": "api/browsersettings/imageanimationbehavior.html", "browserSettings.newTabPageOverride": "api/browsersettings/newtabpageoverride.html", "browserSettings.newTabPosition": "api/browsersettings/newtabposition.html", "browserSettings.openBookmarksInNewTabs": "api/browsersettings/openbookmarksinnewtabs.html", "browserSettings.openSearchResultsInNewTabs": "api/browsersettings/opensearchresultsinnewtabs.html", "browserSettings.openUrlbarResultsInNewTabs": "api/browsersettings/openurlbarresultsinnewtabs.html", "browserSettings.overrideContentColorScheme": "api/browsersettings/overridecontentcolorscheme.html", "browserSettings.overrideDocumentColors": "api/browsersettings/overridedocumentcolors.html", "browserSettings.tlsVersionRestrictionConfig": "api/browsersettings/tlsversionrestrictionconfig.html", "browserSettings.useDocumentFonts": "api/browsersettings/usedocumentfonts.html", "browserSettings.webNotificationsDisabled": "api/browsersettings/webnotificationsdisabled.html", "browserSettings.zoomFullPage": "api/browsersettings/zoomfullpage.html", "browserSettings.zoomSiteSpecific": "api/browsersettings/zoomsitespecific.html", "browsingData": "api/browsingdata.html", "browsingData.DataTypeSet": "api/browsingdata/datatypeset.html", "browsingData.RemovalOptions": "api/browsingdata/removaloptions.html", "browsingData.remove()": "api/browsingdata/remove.html", "browsingData.removeCache()": "api/browsingdata/removecache.html", "browsingData.removeCookies()": "api/browsingdata/removecookies.html", "browsingData.removeDownloads()": "api/browsingdata/removedownloads.html", "browsingData.removeFormData()": "api/browsingdata/removeformdata.html", "browsingData.removeHistory()": "api/browsingdata/removehistory.html", "browsingData.removeLocalStorage()": "api/browsingdata/removelocalstorage.html", "browsingData.removePasswords()": "api/browsingdata/removepasswords.html", "browsingData.removePluginData()": "api/browsingdata/removeplugindata.html", "browsingData.settings()": "api/browsingdata/settings.html", "captivePortal": "api/captiveportal.html", "captivePortal.canonicalURL": "api/captiveportal/canonicalurl.html", "Chrome incompatibilities": "chrome_incompatibilities.html", "chrome_settings_overrides": "manifest.json/chrome_settings_overrides.html", "chrome_url_overrides": "manifest.json/chrome_url_overrides.html", "clear()": "api/types/browsersetting/clear.html", "clipboard": "api/clipboard.html", "clipboard.setImageData()": "api/clipboard/setimagedata.html", "Command": "api/commands/command.html", "commands": "api/commands.html", "commands.reset()": "api/commands/reset.html", "commands.update()": "api/commands/update.html", "Content scripts": "content_scripts.html", "Content Security Policy": "content_security_policy.html", "content_scripts": "manifest.json/content_scripts.html", "content_security_policy": "manifest.json/content_security_policy.html", "contentScripts": "api/contentscripts.html", "contentScripts.register()": "api/contentscripts/register.html", "contentScripts.RegisteredContentScript": "api/contentscripts/registeredcontentscript.html", "contentScripts.RegisteredContentScript.unregister()": "api/contentscripts/registeredcontentscript/unregister.html", "Context menu items": "user_interface/context_menu_items.html", "contextualIdentities": "api/contextualidentities.html", "contextualIdentities.ContextualIdentity": "api/contextualidentities/contextualidentity.html", "contextualIdentities.create()": "api/contextualidentities/create.html", "contextualIdentities.get()": "api/contextualidentities/get.html", "contextualIdentities.onCreated": "api/contextualidentities/oncreated.html", "contextualIdentities.onRemoved": "api/contextualidentities/onremoved.html", "contextualIdentities.onUpdated": "api/contextualidentities/onupdated.html", "contextualIdentities.query()": "api/contextualidentities/query.html", "contextualIdentities.remove()": "api/contextualidentities/remove.html", "contextualIdentities.update()": "api/contextualidentities/update.html", "cookies": "api/cookies.html", "cookies.Cookie": "api/cookies/cookie.html", "cookies.CookieStore": "api/cookies/cookiestore.html", "cookies.get()": "api/cookies/get.html", "cookies.getAll()": "api/cookies/getall.html", "cookies.getAllCookieStores()": "api/cookies/getallcookiestores.html", "cookies.onChanged": "api/cookies/onchanged.html", "cookies.OnChangedCause": "api/cookies/onchangedcause.html", "cookies.remove()": "api/cookies/remove.html", "cookies.SameSiteStatus": "api/cookies/samesitestatus.html", "cookies.set()": "api/cookies/set.html", "declarative_net_request": "manifest.json/declarative_net_request.html", "declarativeNetRequest": "api/declarativenetrequest.html", "declarativeNetRequest.DYNAMIC_RULESET_ID": "api/declarativenetrequest/dynamic_ruleset_id.html", "declarativeNetRequest.getAvailableStaticRuleCount": "api/declarativenetrequest/getavailablestaticrulecount.html", "declarativeNetRequest.getDynamicRules": "api/declarativenetrequest/getdynamicrules.html", "declarativeNetRequest.getEnabledRulesets": "api/declarativenetrequest/getenabledrulesets.html", "declarativeNetRequest.getMatchedRules": "api/declarativenetrequest/getmatchedrules.html", "declarativeNetRequest.GETMATCHEDRULES_QUOTA_INTERVAL": "api/declarativenetrequest/getmatchedrules_quota_interval.html", "declarativeNetRequest.getSessionRules": "api/declarativenetrequest/getsessionrules.html", "declarativeNetRequest.GUARANTEED_MINIMUM_STATIC_RULES": "api/declarativenetrequest/guaranteed_minimum_static_rules.html", "declarativeNetRequest.isRegexSupported": "api/declarativenetrequest/isregexsupported.html", "declarativeNetRequest.MatchedRule": "api/declarativenetrequest/matchedrule.html", "declarativeNetRequest.MAX_GETMATCHEDRULES_CALLS_PER_INTERVAL": "api/declarativenetrequest/max_getmatchedrules_calls_per_interval.html", "declarativeNetRequest.MAX_NUMBER_OF_DYNAMIC_AND_SESSION_RULES": "api/declarativenetrequest/max_number_of_dynamic_and_session_rules.html", "declarativeNetRequest.MAX_NUMBER_OF_ENABLED_STATIC_RULESETS": "api/declarativenetrequest/max_number_of_enabled_static_rulesets.html", "declarativeNetRequest.MAX_NUMBER_OF_REGEX_RULES": "api/declarativenetrequest/max_number_of_regex_rules.html", "declarativeNetRequest.MAX_NUMBER_OF_STATIC_RULESETS": "api/declarativenetrequest/max_number_of_static_rulesets.html", "declarativeNetRequest.ModifyHeaderInfo": "api/declarativenetrequest/modifyheaderinfo.html", "declarativeNetRequest.onRuleMatchedDebug": "api/declarativenetrequest/onrulematcheddebug.html", "declarativeNetRequest.Redirect": "api/declarativenetrequest/redirect.html", "declarativeNetRequest.ResourceType": "api/declarativenetrequest/resourcetype.html", "declarativeNetRequest.Rule": "api/declarativenetrequest/rule.html", "declarativeNetRequest.RuleAction": "api/declarativenetrequest/ruleaction.html", "declarativeNetRequest.RuleCondition": "api/declarativenetrequest/rulecondition.html", "declarativeNetRequest.SESSION_RULESET_ID": "api/declarativenetrequest/session_ruleset_id.html", "declarativeNetRequest.setExtensionActionOptions": "api/declarativenetrequest/setextensionactionoptions.html", "declarativeNetRequest.testMatchOutcome": "api/declarativenetrequest/testmatchoutcome.html", "declarativeNetRequest.updateDynamicRules": "api/declarativenetrequest/updatedynamicrules.html", "declarativeNetRequest.updateEnabledRulesets": "api/declarativenetrequest/updateenabledrulesets.html", "declarativeNetRequest.updateSessionRules": "api/declarativenetrequest/updatesessionrules.html", "declarativeNetRequest.URLTransform": "api/declarativenetrequest/urltransform.html", "default_locale": "manifest.json/default_locale.html", "description": "manifest.json/description.html", "developer": "manifest.json/developer.html", "devtools": "api/devtools.html", "devtools panels": "user_interface/devtools_panels.html", "devtools.inspectedWindow": "api/devtools/inspectedwindow.html", "devtools.inspectedWindow.eval()": "api/devtools/inspectedwindow/eval.html", "devtools.inspectedWindow.reload()": "api/devtools/inspectedwindow/reload.html", "devtools.inspectedWindow.tabId": "api/devtools/inspectedwindow/tabid.html", "devtools.network": "api/devtools/network.html", "devtools.network.getHAR()": "api/devtools/network/gethar.html", "devtools.network.onNavigated": "api/devtools/network/onnavigated.html", "devtools.network.onRequestFinished": "api/devtools/network/onrequestfinished.html", "devtools.panels": "api/devtools/panels.html", "devtools.panels.create()": "api/devtools/panels/create.html", "devtools.panels.elements": "api/devtools/panels/elements.html", "devtools.panels.ElementsPanel": "api/devtools/panels/elementspanel.html", "devtools.panels.ElementsPanel.createSidebarPane()": "api/devtools/panels/elementspanel/createsidebarpane.html", "devtools.panels.ElementsPanel.setExpression()": "api/devtools/panels/extensionsidebarpane/setexpression.html", "devtools.panels.ExtensionPanel": "api/devtools/panels/extensionpanel.html", "devtools.panels.ExtensionSidebarPane": "api/devtools/panels/extensionsidebarpane.html", "devtools.panels.ExtensionSidebarPane.onHidden": "api/devtools/panels/extensionsidebarpane/onhidden.html", "devtools.panels.ExtensionSidebarPane.onShown": "api/devtools/panels/extensionsidebarpane/onshown.html", "devtools.panels.ExtensionSidebarPane.setObject()": "api/devtools/panels/extensionsidebarpane/setobject.html", "devtools.panels.ExtensionSidebarPane.setPage()": "api/devtools/panels/extensionsidebarpane/setpage.html", "devtools.panels.onThemeChanged": "api/devtools/panels/onthemechanged.html", "devtools.panels.themeName": "api/devtools/panels/themename.html", "devtools_page": "manifest.json/devtools_page.html", "dictionaries": "manifest.json/dictionaries.html", "dns": "api/dns.html", "dns.resolve()": "api/dns/resolve.html", "dom": "api/dom.html", "dom.openOrClosedShadowRoot()": "api/dom/openorclosedshadowroot.html", "downloads": "api/downloads.html", "downloads.acceptDanger()": "api/downloads/acceptdanger.html", "downloads.BooleanDelta": "api/downloads/booleandelta.html", "downloads.cancel()": "api/downloads/cancel.html", "downloads.DangerType": "api/downloads/dangertype.html", "downloads.DoubleDelta": "api/downloads/doubledelta.html", "downloads.download()": "api/downloads/download.html", "downloads.DownloadItem": "api/downloads/downloaditem.html", "downloads.DownloadQuery": "api/downloads/downloadquery.html", "downloads.DownloadTime": "api/downloads/downloadtime.html", "downloads.drag()": "api/downloads/drag.html", "downloads.erase()": "api/downloads/erase.html", "downloads.FilenameConflictAction": "api/downloads/filenameconflictaction.html", "downloads.getFileIcon()": "api/downloads/getfileicon.html", "downloads.InterruptReason": "api/downloads/interruptreason.html", "downloads.onChanged": "api/downloads/onchanged.html", "downloads.onCreated": "api/downloads/oncreated.html", "downloads.onErased": "api/downloads/onerased.html", "downloads.open()": "api/downloads/open.html", "downloads.pause()": "api/downloads/pause.html", "downloads.removeFile()": "api/downloads/removefile.html", "downloads.resume()": "api/downloads/resume.html", "downloads.search()": "api/downloads/search.html", "downloads.setShelfEnabled()": "api/downloads/setshelfenabled.html", "downloads.show()": "api/downloads/show.html", "downloads.showDefaultFolder()": "api/downloads/showdefaultfolder.html", "downloads.State": "api/downloads/state.html", "downloads.StringDelta": "api/downloads/stringdelta.html", "events": "api/events.html", "events.Event": "api/events/event.html", "events.Rule": "api/events/rule.html", "events.UrlFilter": "api/events/urlfilter.html", "Example extensions": "examples.html", "Extending the developer tools": "extending_the_developer_tools.html", "extension": "api/extension.html", "Extension pages": "user_interface/extension_pages.html", "extension.getBackgroundPage()": "api/extension/getbackgroundpage.html", "extension.getExtensionTabs()": "api/extension/getextensiontabs.html", "extension.getURL()": "api/extension/geturl.html", "extension.getViews()": "api/extension/getviews.html", "extension.inIncognitoContext": "api/extension/inincognitocontext.html", "extension.isAllowedFileSchemeAccess()": "api/extension/isallowedfileschemeaccess.html", "extension.isAllowedIncognitoAccess()": "api/extension/isallowedincognitoaccess.html", "extension.lastError": "api/extension/lasterror.html", "extension.onRequest": "api/extension/onrequest.html", "extension.onRequestExternal": "api/extension/onrequestexternal.html", "extension.sendRequest()": "api/extension/sendrequest.html", "extension.setUpdateUrlData()": "api/extension/setupdateurldata.html", "extension.ViewType": "api/extension/viewtype.html", "ExtensionInfo": "api/management/extensioninfo.html", "extensionTypes": "api/extensiontypes.html", "extensionTypes.ImageDetails": "api/extensiontypes/imagedetails.html", "extensionTypes.ImageFormat": "api/extensiontypes/imageformat.html", "extensionTypes.InjectDetails": "api/extensiontypes/injectdetails.html", "extensionTypes.RunAt": "api/extensiontypes/runat.html", "externally_connectable": "manifest.json/externally_connectable.html", "find": "api/find.html", "find.find()": "api/find/find.html", "find.highlightResults()": "api/find/highlightresults.html", "find.removeHighlighting()": "api/find/removehighlighting.html", "Firefox workflow overview": "firefox_workflow_overview.html", "get()": "api/types/browsersetting/get.html", "getAll()": "api/commands/getall.html", "getLastChecked": "api/captiveportal/getlastchecked.html", "getState": "api/captiveportal/getstate.html", "history": "api/history.html", "history.addUrl()": "api/history/addurl.html", "history.deleteAll()": "api/history/deleteall.html", "history.deleteRange()": "api/history/deleterange.html", "history.deleteUrl()": "api/history/deleteurl.html", "history.getVisits()": "api/history/getvisits.html", "history.HistoryItem": "api/history/historyitem.html", "history.onTitleChanged": "api/history/ontitlechanged.html", "history.onVisited": "api/history/onvisited.html", "history.onVisitRemoved": "api/history/onvisitremoved.html", "history.search()": "api/history/search.html", "history.TransitionType": "api/history/transitiontype.html", "history.VisitItem": "api/history/visititem.html", "homepage_url": "manifest.json/homepage_url.html", "host_permissions": "manifest.json/host_permissions.html", "i18n": "api/i18n.html", "i18n.detectLanguage()": "api/i18n/detectlanguage.html", "i18n.getAcceptLanguages()": "api/i18n/getacceptlanguages.html", "i18n.getMessage()": "api/i18n/getmessage.html", "i18n.getUILanguage()": "api/i18n/getuilanguage.html", "i18n.LanguageCode": "api/i18n/languagecode.html", "icons": "manifest.json/icons.html", "identity": "api/identity.html", "identity.getRedirectURL()": "api/identity/getredirecturl.html", "identity.launchWebAuthFlow": "api/identity/launchwebauthflow.html", "idle": "api/idle.html", "idle.IdleState": "api/idle/idlestate.html", "idle.onStateChanged": "api/idle/onstatechanged.html", "idle.queryState()": "api/idle/querystate.html", "idle.setDetectionInterval()": "api/idle/setdetectioninterval.html", "Implement a settings page": "implement_a_settings_page.html", "incognito": "manifest.json/incognito.html", "Interact with the clipboard": "interact_with_the_clipboard.html", "Intercept HTTP requests": "intercept_http_requests.html", "Internationalization": "internationalization.html", "JavaScript APIs": "api.html", "Legacy Version Formats": "manifest.json/version/format.html", "Locale-specific message reference": "api/i18n/locale-specific_message_reference.html", "management": "api/management.html", "management.get()": "api/management/get.html", "management.getAll()": "api/management/getall.html", "management.getPermissionWarningsById()": "api/management/getpermissionwarningsbyid.html", "management.getPermissionWarningsByManifest()": "api/management/getpermissionwarningsbymanifest.html", "management.getSelf()": "api/management/getself.html", "management.install()": "api/management/install.html", "management.onDisabled()": "api/management/ondisabled.html", "management.onEnabled()": "api/management/onenabled.html", "management.onInstalled()": "api/management/oninstalled.html", "management.onUninstalled()": "api/management/onuninstalled.html", "management.setEnabled()": "api/management/setenabled.html", "management.uninstall()": "api/management/uninstall.html", "management.uninstallSelf()": "api/management/uninstallself.html", "manifest.json": "manifest.json.html", "manifest_version": "manifest.json/manifest_version.html", "Match patterns in extension manifests": "match_patterns.html", "menus": "api/menus.html", "menus.ACTION_MENU_TOP_LEVEL_LIMIT": "api/menus/action_menu_top_level_limit.html", "menus.ContextType": "api/menus/contexttype.html", "menus.create()": "api/menus/create.html", "menus.getTargetElement()": "api/menus/gettargetelement.html", "menus.ItemType": "api/menus/itemtype.html", "menus.OnClickData": "api/menus/onclickdata.html", "menus.onClicked": "api/menus/onclicked.html", "menus.onHidden": "api/menus/onhidden.html", "menus.onShown": "api/menus/onshown.html", "menus.overrideContext()": "api/menus/overridecontext.html", "menus.refresh()": "api/menus/refresh.html", "menus.remove()": "api/menus/remove.html", "menus.removeAll()": "api/menus/removeall.html", "menus.update()": "api/menus/update.html", "Modify a web page": "modify_a_web_page.html", "name": "manifest.json/name.html", "Native manifests": "native_manifests.html", "Native messaging": "native_messaging.html", "notifications": "api/notifications.html", "Notifications": "user_interface/notifications.html", "notifications.clear()": "api/notifications/clear.html", "notifications.create()": "api/notifications/create.html", "notifications.getAll()": "api/notifications/getall.html", "notifications.NotificationOptions": "api/notifications/notificationoptions.html", "notifications.onButtonClicked": "api/notifications/onbuttonclicked.html", "notifications.onClicked": "api/notifications/onclicked.html", "notifications.onClosed": "api/notifications/onclosed.html", "notifications.onShown": "api/notifications/onshown.html", "notifications.TemplateType": "api/notifications/templatetype.html", "notifications.update()": "api/notifications/update.html", "offline_enabled": "manifest.json/offline_enabled.html", "omnibox": "manifest.json/omnibox.html", "omnibox.onDeleteSuggestion": "api/omnibox/ondeletesuggestion.html", "omnibox.onInputCancelled": "api/omnibox/oninputcancelled.html", "omnibox.onInputChanged": "api/omnibox/oninputchanged.html", "omnibox.onInputEntered": "api/omnibox/oninputentered.html", "omnibox.OnInputEnteredDisposition": "api/omnibox/oninputentereddisposition.html", "omnibox.onInputStarted": "api/omnibox/oninputstarted.html", "omnibox.setDefaultSuggestion()": "api/omnibox/setdefaultsuggestion.html", "omnibox.SuggestResult": "api/omnibox/suggestresult.html", "onCommand": "api/commands/oncommand.html", "onConnectivityAvailable": "api/captiveportal/onconnectivityavailable.html", "onStateChanged": "api/captiveportal/onstatechanged.html", "optional_permissions": "manifest.json/optional_permissions.html", "Options page": "user_interface/options_pages.html", "options_page": "manifest.json/options_page.html", "options_ui": "manifest.json/options_ui.html", "page_action": "manifest.json/page_action.html", "pageAction": "api/pageaction.html", "pageAction.getPopup()": "api/pageaction/getpopup.html", "pageAction.getTitle()": "api/pageaction/gettitle.html", "pageAction.hide()": "api/pageaction/hide.html", "pageAction.ImageDataType": "api/pageaction/imagedatatype.html", "pageAction.isShown()": "api/pageaction/isshown.html", "pageAction.onClicked": "api/pageaction/onclicked.html", "pageAction.openPopup()": "api/pageaction/openpopup.html", "pageAction.setIcon()": "api/pageaction/seticon.html", "pageAction.setPopup()": "api/pageaction/setpopup.html", "pageAction.setTitle()": "api/pageaction/settitle.html", "pageAction.show()": "api/pageaction/show.html", "permissions": "manifest.json/permissions.html", "Permissions": "api/permissions/permissions.html", "permissions.contains()": "api/permissions/contains.html", "permissions.getAll()": "api/permissions/getall.html", "permissions.onAdded": "api/permissions/onadded.html", "permissions.onRemoved": "api/permissions/onremoved.html", "permissions.remove()": "api/permissions/remove.html", "permissions.request()": "api/permissions/request.html", "pkcs11": "api/pkcs11.html", "pkcs11.getModuleSlots()": "api/pkcs11/getmoduleslots.html", "pkcs11.installModule()": "api/pkcs11/installmodule.html", "pkcs11.isModuleInstalled()": "api/pkcs11/ismoduleinstalled.html", "pkcs11.uninstallModule()": "api/pkcs11/uninstallmodule.html", "Popups": "user_interface/popups.html", "privacy": "api/privacy.html", "privacy.network": "api/privacy/network.html", "privacy.services": "api/privacy/services.html", "privacy.websites": "api/privacy/websites.html", "protocol_handlers": "manifest.json/protocol_handlers.html", "proxy": "api/proxy.html", "proxy.onError": "api/proxy/onerror.html", "proxy.onRequest": "api/proxy/onrequest.html", "proxy.ProxyInfo": "api/proxy/proxyinfo.html", "proxy.register()": "api/proxy/register.html", "proxy.RequestDetails": "api/proxy/requestdetails.html", "proxy.settings": "api/proxy/settings.html", "proxy.unregister()": "api/proxy/unregister.html", "RegisteredUserScript.unregister()": "api/userscripts/registereduserscript/unregister.html", "runtime": "api/runtime.html", "runtime.connect()": "api/runtime/connect.html", "runtime.connectNative()": "api/runtime/connectnative.html", "runtime.getBackgroundPage()": "api/runtime/getbackgroundpage.html", "runtime.getBrowserInfo()": "api/runtime/getbrowserinfo.html", "runtime.getFrameId()": "api/runtime/getframeid.html", "runtime.getManifest()": "api/runtime/getmanifest.html", "runtime.getPackageDirectoryEntry()": "api/runtime/getpackagedirectoryentry.html", "runtime.getPlatformInfo()": "api/runtime/getplatforminfo.html", "runtime.getURL()": "api/runtime/geturl.html", "runtime.id": "api/runtime/id.html", "runtime.lastError": "api/runtime/lasterror.html", "runtime.MessageSender": "api/runtime/messagesender.html", "runtime.onBrowserUpdateAvailable": "api/runtime/onbrowserupdateavailable.html", "runtime.onConnect": "api/runtime/onconnect.html", "runtime.onConnectExternal": "api/runtime/onconnectexternal.html", "runtime.onInstalled": "api/runtime/oninstalled.html", "runtime.OnInstalledReason": "api/runtime/oninstalledreason.html", "runtime.onMessage": "api/runtime/onmessage.html", "runtime.onMessageExternal": "api/runtime/onmessageexternal.html", "runtime.onRestartRequired": "api/runtime/onrestartrequired.html", "runtime.OnRestartRequiredReason": "api/runtime/onrestartrequiredreason.html", "runtime.onStartup": "api/runtime/onstartup.html", "runtime.onSuspend": "api/runtime/onsuspend.html", "runtime.onSuspendCanceled": "api/runtime/onsuspendcanceled.html", "runtime.onUpdateAvailable": "api/runtime/onupdateavailable.html", "runtime.openOptionsPage()": "api/runtime/openoptionspage.html", "runtime.PlatformArch": "api/runtime/platformarch.html", "runtime.PlatformInfo": "api/runtime/platforminfo.html", "runtime.PlatformNaclArch": "api/runtime/platformnaclarch.html", "runtime.PlatformOs": "api/runtime/platformos.html", "runtime.Port": "api/runtime/port.html", "runtime.reload()": "api/runtime/reload.html", "runtime.requestUpdateCheck()": "api/runtime/requestupdatecheck.html", "runtime.RequestUpdateCheckStatus": "api/runtime/requestupdatecheckstatus.html", "runtime.sendMessage()": "api/runtime/sendmessage.html", "runtime.sendNativeMessage()": "api/runtime/sendnativemessage.html", "runtime.setUninstallURL()": "api/runtime/setuninstallurl.html", "scripting": "api/scripting.html", "scripting.ContentScriptFilter": "api/scripting/contentscriptfilter.html", "scripting.executeScript()": "api/scripting/executescript.html", "scripting.ExecutionWorld": "api/scripting/executionworld.html", "scripting.getRegisteredContentScripts()": "api/scripting/getregisteredcontentscripts.html", "scripting.InjectionTarget": "api/scripting/injectiontarget.html", "scripting.insertCSS()": "api/scripting/insertcss.html", "scripting.registerContentScripts()": "api/scripting/registercontentscripts.html", "scripting.RegisteredContentScript": "api/scripting/registeredcontentscript.html", "scripting.removeCSS()": "api/scripting/removecss.html", "scripting.unregisterContentScripts()": "api/scripting/unregistercontentscripts.html", "scripting.updateContentScripts()": "api/scripting/updatecontentscripts.html", "search": "api/search.html", "search.get()": "api/search/get.html", "search.query()": "api/search/query.html", "search.search()": "api/search/search.html", "sessions": "api/sessions.html", "sessions.Filter": "api/sessions/filter.html", "sessions.forgetClosedTab()": "api/sessions/forgetclosedtab.html", "sessions.forgetClosedWindow()": "api/sessions/forgetclosedwindow.html", "sessions.getRecentlyClosed()": "api/sessions/getrecentlyclosed.html", "sessions.getTabValue()": "api/sessions/gettabvalue.html", "sessions.getWindowValue()": "api/sessions/getwindowvalue.html", "sessions.MAX_SESSION_RESULTS": "api/sessions/max_session_results.html", "sessions.onChanged": "api/sessions/onchanged.html", "sessions.removeTabValue()": "api/sessions/removetabvalue.html", "sessions.removeWindowValue()": "api/sessions/removewindowvalue.html", "sessions.restore()": "api/sessions/restore.html", "sessions.Session": "api/sessions/session.html", "sessions.setTabValue()": "api/sessions/settabvalue.html", "sessions.setWindowValue()": "api/sessions/setwindowvalue.html", "set()": "api/types/browsersetting/set.html", "Sharing objects with page scripts": "sharing_objects_with_page_scripts.html", "short_name": "manifest.json/short_name.html", "sidebar_action": "manifest.json/sidebar_action.html", "sidebarAction": "api/sidebaraction.html", "sidebarAction.close()": "api/sidebaraction/close.html", "sidebarAction.getPanel()": "api/sidebaraction/getpanel.html", "sidebarAction.getTitle()": "api/sidebaraction/gettitle.html", "sidebarAction.ImageDataType": "api/sidebaraction/imagedatatype.html", "sidebarAction.isOpen()": "api/sidebaraction/isopen.html", "sidebarAction.open()": "api/sidebaraction/open.html", "sidebarAction.setIcon()": "api/sidebaraction/seticon.html", "sidebarAction.setPanel()": "api/sidebaraction/setpanel.html", "sidebarAction.setTitle()": "api/sidebaraction/settitle.html", "sidebarAction.toggle()": "api/sidebaraction/toggle.html", "Sidebars": "user_interface/sidebars.html", "storage": "manifest.json/storage.html", "storage.local": "api/storage/local.html", "storage.managed": "api/storage/managed.html", "storage.onChanged": "api/storage/onchanged.html", "storage.session": "api/storage/session.html", "storage.StorageArea": "api/storage/storagearea.html", "storage.StorageArea.onChanged": "api/storage/storagearea/onchanged.html", "storage.StorageChange": "api/storage/storagechange.html", "storage.sync": "api/storage/sync.html", "StorageArea.clear()": "api/storage/storagearea/clear.html", "StorageArea.get()": "api/storage/storagearea/get.html", "StorageArea.getBytesInUse()": "api/storage/storagearea/getbytesinuse.html", "StorageArea.remove()": "api/storage/storagearea/remove.html", "StorageArea.set()": "api/storage/storagearea/set.html", "StorageArea.setAccessLevel()": "api/storage/storagearea/setaccesslevel.html", "tabs": "api/tabs.html", "tabs.captureTab()": "api/tabs/capturetab.html", "tabs.captureVisibleTab()": "api/tabs/capturevisibletab.html", "tabs.connect()": "api/tabs/connect.html", "tabs.create()": "api/tabs/create.html", "tabs.detectLanguage()": "api/tabs/detectlanguage.html", "tabs.discard()": "api/tabs/discard.html", "tabs.duplicate()": "api/tabs/duplicate.html", "tabs.executeScript()": "api/tabs/executescript.html", "tabs.get()": "api/tabs/get.html", "tabs.getAllInWindow()": "api/tabs/getallinwindow.html", "tabs.getCurrent()": "api/tabs/getcurrent.html", "tabs.getSelected()": "api/tabs/getselected.html", "tabs.getZoom()": "api/tabs/getzoom.html", "tabs.getZoomSettings()": "api/tabs/getzoomsettings.html", "tabs.goBack()": "api/tabs/goback.html", "tabs.goForward()": "api/tabs/goforward.html", "tabs.hide()": "api/tabs/hide.html", "tabs.highlight()": "api/tabs/highlight.html", "tabs.insertCSS()": "api/tabs/insertcss.html", "tabs.move()": "api/tabs/move.html", "tabs.moveInSuccession()": "api/tabs/moveinsuccession.html", "tabs.MutedInfo": "api/tabs/mutedinfo.html", "tabs.MutedInfoReason": "api/tabs/mutedinforeason.html", "tabs.onActivated": "api/tabs/onactivated.html", "tabs.onActiveChanged": "api/tabs/onactivechanged.html", "tabs.onAttached": "api/tabs/onattached.html", "tabs.onCreated": "api/tabs/oncreated.html", "tabs.onDetached": "api/tabs/ondetached.html", "tabs.onHighlightChanged": "api/tabs/onhighlightchanged.html", "tabs.onHighlighted": "api/tabs/onhighlighted.html", "tabs.onMoved": "api/tabs/onmoved.html", "tabs.onRemoved": "api/tabs/onremoved.html", "tabs.onReplaced": "api/tabs/onreplaced.html", "tabs.onSelectionChanged": "api/tabs/onselectionchanged.html", "tabs.onUpdated": "api/tabs/onupdated.html", "tabs.onZoomChange": "api/tabs/onzoomchange.html", "tabs.PageSettings": "api/tabs/pagesettings.html", "tabs.print()": "api/tabs/print.html", "tabs.printPreview()": "api/tabs/printpreview.html", "tabs.query()": "api/tabs/query.html", "tabs.reload()": "api/tabs/reload.html", "tabs.remove()": "api/tabs/remove.html", "tabs.removeCSS()": "api/tabs/removecss.html", "tabs.saveAsPDF()": "api/tabs/saveaspdf.html", "tabs.sendMessage()": "api/tabs/sendmessage.html", "tabs.sendRequest()": "api/tabs/sendrequest.html", "tabs.setZoom()": "api/tabs/setzoom.html", "tabs.setZoomSettings()": "api/tabs/setzoomsettings.html", "tabs.show()": "api/tabs/show.html", "tabs.Tab": "api/tabs/tab.html", "tabs.TAB_ID_NONE": "api/tabs/tab_id_none.html", "tabs.TabStatus": "api/tabs/tabstatus.html", "tabs.toggleReaderMode()": "api/tabs/togglereadermode.html", "tabs.update()": "api/tabs/update.html", "tabs.warmup()": "api/tabs/warmup.html", "tabs.WindowType": "api/tabs/windowtype.html", "tabs.ZoomSettings": "api/tabs/zoomsettings.html", "tabs.ZoomSettingsMode": "api/tabs/zoomsettingsmode.html", "tabs.ZoomSettingsScope": "api/tabs/zoomsettingsscope.html", "theme": "api/theme.html", "Theme": "api/theme/theme.html", "theme.getCurrent()": "api/theme/getcurrent.html", "theme.onUpdated": "api/theme/onupdated.html", "theme.reset()": "api/theme/reset.html", "theme.update()": "api/theme/update.html", "theme_experiment": "manifest.json/theme_experiment.html", "Toolbar button": "user_interface/browser_action.html", "topSites": "api/topsites.html", "topSites.get()": "api/topsites/get.html", "topSites.MostVisitedURL": "api/topsites/mostvisitedurl.html", "types": "api/types.html", "User actions": "user_actions.html", "User interface": "user_interface.html", "user_scripts": "manifest.json/user_scripts.html", "userScripts": "api/userscripts.html", "userScripts.onBeforeScript": "api/userscripts/onbeforescript.html", "userScripts.register()": "api/userscripts/register.html", "userScripts.RegisteredUserScript": "api/userscripts/registereduserscript.html", "version": "manifest.json/version.html", "version_name": "manifest.json/version_name.html", "web_accessible_resources": "manifest.json/web_accessible_resources.html", "webNavigation": "api/webnavigation.html", "webNavigation.getAllFrames()": "api/webnavigation/getallframes.html", "webNavigation.getFrame()": "api/webnavigation/getframe.html", "webNavigation.onBeforeNavigate": "api/webnavigation/onbeforenavigate.html", "webNavigation.onCommitted": "api/webnavigation/oncommitted.html", "webNavigation.onCompleted": "api/webnavigation/oncompleted.html", "webNavigation.onCreatedNavigationTarget": "api/webnavigation/oncreatednavigationtarget.html", "webNavigation.onDOMContentLoaded": "api/webnavigation/ondomcontentloaded.html", "webNavigation.onErrorOccurred": "api/webnavigation/onerroroccurred.html", "webNavigation.onHistoryStateUpdated": "api/webnavigation/onhistorystateupdated.html", "webNavigation.onReferenceFragmentUpdated": "api/webnavigation/onreferencefragmentupdated.html", "webNavigation.onTabReplaced": "api/webnavigation/ontabreplaced.html", "webNavigation.TransitionQualifier": "api/webnavigation/transitionqualifier.html", "webNavigation.TransitionType": "api/webnavigation/transitiontype.html", "webRequest": "api/webrequest.html", "webRequest.BlockingResponse": "api/webrequest/blockingresponse.html", "webRequest.CertificateInfo": "api/webrequest/certificateinfo.html", "webRequest.filterResponseData()": "api/webrequest/filterresponsedata.html", "webRequest.getSecurityInfo()": "api/webrequest/getsecurityinfo.html", "webRequest.handlerBehaviorChanged()": "api/webrequest/handlerbehaviorchanged.html", "webRequest.HttpHeaders": "api/webrequest/httpheaders.html", "webRequest.MAX_HANDLER_BEHAVIOR_CHANGED_CALLS_PER_10_MINUTES": "api/webrequest/max_handler_behavior_changed_calls_per_10_minutes.html", "webRequest.onAuthRequired": "api/webrequest/onauthrequired.html", "webRequest.onBeforeRedirect": "api/webrequest/onbeforeredirect.html", "webRequest.onBeforeRequest": "api/webrequest/onbeforerequest.html", "webRequest.onBeforeSendHeaders": "api/webrequest/onbeforesendheaders.html", "webRequest.onCompleted": "api/webrequest/oncompleted.html", "webRequest.onErrorOccurred": "api/webrequest/onerroroccurred.html", "webRequest.onHeadersReceived": "api/webrequest/onheadersreceived.html", "webRequest.onResponseStarted": "api/webrequest/onresponsestarted.html", "webRequest.onSendHeaders": "api/webrequest/onsendheaders.html", "webRequest.RequestFilter": "api/webrequest/requestfilter.html", "webRequest.ResourceType": "api/webrequest/resourcetype.html", "webRequest.SecurityInfo": "api/webrequest/securityinfo.html", "webRequest.StreamFilter": "api/webrequest/streamfilter.html", "webRequest.StreamFilter.close()": "api/webrequest/streamfilter/close.html", "webRequest.StreamFilter.disconnect()": "api/webrequest/streamfilter/disconnect.html", "webRequest.StreamFilter.error": "api/webrequest/streamfilter/error.html", "webRequest.StreamFilter.ondata": "api/webrequest/streamfilter/ondata.html", "webRequest.StreamFilter.onerror": "api/webrequest/streamfilter/onerror.html", "webRequest.StreamFilter.onstart": "api/webrequest/streamfilter/onstart.html", "webRequest.StreamFilter.onstop": "api/webrequest/streamfilter/onstop.html", "webRequest.StreamFilter.resume()": "api/webrequest/streamfilter/resume.html", "webRequest.StreamFilter.status": "api/webrequest/streamfilter/status.html", "webRequest.StreamFilter.suspend()": "api/webrequest/streamfilter/suspend.html", "webRequest.StreamFilter.write()": "api/webrequest/streamfilter/write.html", "webRequest.UploadData": "api/webrequest/uploaddata.html", "What are extensions?": "what_are_webextensions.html", "What next?": "what_next_.html", "windows": "api/windows.html", "windows.create()": "api/windows/create.html", "windows.CreateType": "api/windows/createtype.html", "windows.get()": "api/windows/get.html", "windows.getAll()": "api/windows/getall.html", "windows.getCurrent()": "api/windows/getcurrent.html", "windows.getLastFocused()": "api/windows/getlastfocused.html", "windows.onCreated": "api/windows/oncreated.html", "windows.onFocusChanged": "api/windows/onfocuschanged.html", "windows.onRemoved": "api/windows/onremoved.html", "windows.remove()": "api/windows/remove.html", "windows.update()": "api/windows/update.html", "windows.Window": "api/windows/window.html", "windows.WINDOW_ID_CURRENT": "api/windows/window_id_current.html", "windows.WINDOW_ID_NONE": "api/windows/window_id_none.html", "windows.WindowState": "api/windows/windowstate.html", "windows.WindowType": "api/windows/windowtype.html", "Work with contextual identities": "work_with_contextual_identities.html", "Working with files": "working_with_files.html", "Working with the Tabs API": "working_with_the_tabs_api.html", "Working with userScripts": "api/userscripts/working_with_userscripts.html", "Your first extension": "your_first_webextension.html", "Your second extension": "your_second_webextension.html"}